runwith/__init__.py
runwith/__main__.py
runwith/version.txt
runwith-0.1.0.dist-info/DESCRIPTION.rst
runwith-0.1.0.dist-info/METADATA
runwith-0.1.0.dist-info/RECORD
runwith-0.1.0.dist-info/WHEEL
runwith-0.1.0.dist-info/entry_points.txt
runwith-0.1.0.dist-info/metadata.json
runwith-0.1.0.dist-info/top_level.txt
