Metadata-Version: 2.0
Name: runwith
Version: 0.1.0
Summary: Poor man's shell operations
Home-page: https://github.com/AndreLouisCaron/runwith
Author: Andre Caron
Author-email: andre.l.caron@gmail.com
License: UNKNOWN
Platform: UNKNOWN
